bareBonesWeb/__cache.py
bareBonesWeb/__init__.py
bareBonesWeb/bareboneswebCLI.py
bareBonesWeb/framework/cli.py
bareBonesWeb/framework/forms.py
bareBonesWeb/framework/httpInteractions.py
bareBonesWeb/framework/urlTools.py
bareBonesWeb/framework/data_representation/charts.py
bareBonesWeb/framework/database/Database.py
bareBonesWeb/framework/database/bare_database.py
bareBonesWeb/framework/database/db.c
bareBonesWeb/framework/database/sqlite.py
bareBonesWeb/framework/file_loading/static.py
bareBonesWeb/framework/file_loading/templates.py
barebonesweb-1.0.4.dist-info/METADATA
barebonesweb-1.0.4.dist-info/WHEEL
barebonesweb-1.0.4.dist-info/entry_points.txt
barebonesweb-1.0.4.dist-info/RECORD
