Metadata-Version: 2.4
Name: bareBonesWeb
Version: 1.0.4
Summary: A python web framework only using modules that are already installed on python Soon i will try to minimize the ammount of python packages to make it truly standalone
Author: DaproDX
Keywords: framework,web,wsgi
Requires-Python: >=3.8
